[{"properties":{"Name":"Stol (OK-17289F)","Objekt-ID":"OK-17289F","Betegnelse":"Stol","Datering":"1820-tallet","Nasjonalmuseet":"https://www.nasjonalmuseet.no/samlingen/objekt/OK-17289F","Erverving":"Ervervet 1953","Produksjonsstad":"Norge","Materialkommentar":"Bjørk, beiset og lakkert, dreid dekor, marketeri i buksbom og jakaranda, polstret sete med hestehårstrekk","Mål":"H 81 x B 47,8 x D 50 cm Bredde: 47,8 cm Dybde: 41,5 cm Høyde: 50 cm","Hundreår":"1800-talet","Frå år":1820,"Til år":1820,"Høgde (cm)":81,"Breidde (cm)":47.8,"Djupn (cm)":50,"Setehøgde (cm)":50,"Materialar":"[\"Bjørk\",\"Messing\",\"Jakaranda\",\"Buksbom\",\"Hestetagl\"]","Teknikk":"[\"Polstring\",\"Tapping\"]","Emneord":"[\"Møbel\"]"},"content":"<image source=\"https://ms01.nasjonalmuseet.no/iip/?iiif=/tif/92648.tif/full/full/0/default.jpg\">OK-17289F</image>"},{"properties":{"Name":"Stol (OK-17289D)","Objekt-ID":"OK-17289D","Betegnelse":"Stol","Datering":"1820-tallet","Nasjonalmuseet":"https://www.nasjonalmuseet.no/samlingen/objekt/OK-17289D","Erverving":"Ervervet 1953","Produksjonsstad":"Norge","Materialkommentar":"Bjørk, beiset og lakkert, dreid dekor, marketeri i buksbom og jakaranda, polstret sete med hestehårstrekk","Mål":"H 79,8 x B 48 x D 52 cm Høyde: 52 cm Dybde: 48 cm Bredde: 48 cm","Hundreår":"1800-talet","Frå år":1820,"Til år":1820,"Høgde (cm)":79.8,"Breidde (cm)":48,"Djupn (cm)":52,"Setehøgde (cm)":52,"Materialar":"[\"Bjørk\",\"Messing\",\"Buksbom\",\"Hestetagl\",\"Jakaranda\"]","Teknikk":"[\"Polstring\",\"Tapping\"]","Emneord":"[\"Møbel\"]"},"content":"<image source=\"https://ms01.nasjonalmuseet.no/iip/?iiif=/tif/92649.tif/full/full/0/default.jpg\">OK-17289D</image>"},{"properties":{"Name":"Stol (OK-15056B-1)","Objekt-ID":"OK-15056B-1","Betegnelse":"Stol","Datering":"1889","Nasjonalmuseet":"https://www.nasjonalmuseet.no/samlingen/objekt/OK-15056B-1","Erverving":"Gave 1958","Produksjonsstad":"Norge","Materialkommentar":"Beiset eikestol med skåret og dreid dekor og flettet rotting.","Mål":"H 102 x B 46,5 x D 60,3 cm Høyde: 46,7 cm Bredde: 46,5 cm Dybde: 45,3 cm","Hundreår":"1800-talet","Frå år":1889,"Til år":1889,"Høgde (cm)":102,"Breidde (cm)":46.5,"Djupn (cm)":60.3,"Setehøgde (cm)":46.7,"Materialar":"[\"Eik\",\"Palme\"]","Teknikk":"[\"Fletting\",\"Tapping\",\"Innfelling / rammeverk med fylling\"]","Emneord":"[\"Møbel\"]"},"content":"<image source=\"https://ms01.nasjonalmuseet.no/iip/?iiif=/tif/94840.tif/full/full/0/default.jpg\">OK-15056B-1</image>"},{"properties":{"Name":"Stol (OK-15056B-2)","Objekt-ID":"OK-15056B-2","Betegnelse":"Stol","Datering":"1889","Nasjonalmuseet":"https://www.nasjonalmuseet.no/samlingen/objekt/OK-15056B-2","Erverving":"Gave 1958","Produksjonsstad":"Norge","Materialkommentar":"Beiset eikestol med skåret og dreid dekor og flettet rotting.","Mål":"H 102,5 x, B 46,5 x D 59,5 cm Høyde: 48 cm Dybde: 45,5 cm Bredde: 46,5 cm","Hundreår":"1800-talet","Frå år":1889,"Til år":1889,"Setehøgde (cm)":48,"Materialar":"[\"Eik\",\"Palme\"]","Teknikk":"[\"Fletting\",\"Tapping\",\"Innfelling / rammeverk med fylling\"]","Emneord":"[\"Møbel\"]"},"content":"<image source=\"https://ms01.nasjonalmuseet.no/iip/?iiif=/tif/94841.tif/full/full/0/default.jpg\">OK-15056B-2</image>"},{"properties":{"Name":"Stol (OK-07968)","Objekt-ID":"OK-07968","Betegnelse":"Stol","Datering":"begynnelsen av 1700-tallet","Nasjonalmuseet":"https://www.nasjonalmuseet.no/samlingen/objekt/OK-07968","Erverving":"Kjøpt 1908","Produksjonsstad":"Norge","Materialkommentar":"Bøk med skåret og dreid dekor, gyllenlærstrekk.","Mål":"H 125 x B 46 x D 53 cm Dybde: 37,5 cm","Stilperiode":"Barokk","Hundreår":"1700-talet","Frå år":1700,"Til år":1700,"Høgde (cm)":125,"Breidde (cm)":46,"Djupn (cm)":53,"Materialar":"[\"Bøk\",\"Lær\"]","Teknikk":"[\"Tapping\",\"Plugging\"]","Emneord":"[\"Møbel\"]"},"content":"<image source=\"https://ms01.nasjonalmuseet.no/iip/?iiif=/tif/07267.tif/full/full/0/default.jpg\">OK-07968</image>"},{"properties":{"Name":"Stol (OK-11813I)","Objekt-ID":"OK-11813I","Betegnelse":"Stol","Datering":"Antagelig 1840-tallet","Nasjonalmuseet":"https://www.nasjonalmuseet.no/samlingen/objekt/OK-11813I","Erverving":"Gave 1946","Produksjonsstad":"Norge","Materialkommentar":"Skåret og beiset mahogni, polstret sete trukket med plysj","Mål":"H 92 x B 46 x D 52 cm Dybde: 37 cm Høyde: 52 cm Bredde: 45 cm","Hundreår":"1800-talet","Frå år":1840,"Til år":1840,"Høgde (cm)":92,"Breidde (cm)":46,"Djupn (cm)":52,"Setehøgde (cm)":52,"Materialar":"[\"Mahogni\",\"Plysj\"]","Teknikk":"[\"Polstring\",\"Tapping\"]","Emneord":"[\"Møbel\"]"},"content":"<image source=\"https://ms01.nasjonalmuseet.no/iip/?iiif=/tif/94827.tif/full/full/0/default.jpg\">OK-11813I</image>"},{"properties":{"Name":"Stol (OK-02782)","Objekt-ID":"OK-02782","Betegnelse":"Stol","Datering":"begynnelsen av 1700-tallet","Nasjonalmuseet":"https://www.nasjonalmuseet.no/samlingen/objekt/OK-02782","Erverving":"kjøpt 1886","Produksjonsstad":"Norge","Materialkommentar":"Ask og or med dreid og skåret dekor, gyllenlærstrekk","Mål":"H 126,5 x B 54,5 x D 54,5 cm Dybde: 39 cm Bredde: 47 cm Høyde: 44 cm","Stilperiode":"Barokk","Hundreår":"1700-talet","Frå år":1700,"Til år":1700,"Høgde (cm)":126.5,"Breidde (cm)":54.5,"Djupn (cm)":54.5,"Setehøgde (cm)":44,"Materialar":"[\"Ask\",\"Or\",\"Lær\"]","Teknikk":"[\"Polstring\",\"Tapping\",\"Plugging\"]","Emneord":"[\"Møbel\"]"},"content":"<image source=\"https://ms01.nasjonalmuseet.no/iip/?iiif=/tif/07407.tif/full/full/0/default.jpg\">OK-02782</image>"},{"properties":{"Name":"Stol (OK-02781)","Objekt-ID":"OK-02781","Betegnelse":"Stol","Datering":"Begynnelsen av 1700-tallet","Nasjonalmuseet":"https://www.nasjonalmuseet.no/samlingen/objekt/OK-02781","Erverving":"Kjøpt 1886","Produksjonsstad":"Norge","Materialkommentar":"Ask og or med skåret og dreid dekor, gyllenlærstrekk","Mål":"H 126 x B 53,5 x D 53,5 cm Dybde: 39 cm Bredde: 46,5 cm Høyde: 44 cm","Stilperiode":"Barokk","Hundreår":"1700-talet","Frå år":1700,"Til år":1700,"Høgde (cm)":126,"Breidde (cm)":53.5,"Djupn (cm)":53.5,"Setehøgde (cm)":44,"Materialar":"[\"Ask\",\"Or\",\"Lær\",\"Lin\"]","Teknikk":"[\"Polstring\",\"Tapping\",\"Plugging\"]","Emneord":"[\"Møbel\"]"},"content":"<image source=\"https://ms01.nasjonalmuseet.no/iip/?iiif=/tif/07303.tif/full/full/0/default.jpg\">OK-02781</image>"},{"properties":{"Name":"Stol (OK-1980-0045)","Objekt-ID":"OK-1980-0045","Betegnelse":"Stol","Datering":"1979","Nasjonalmuseet":"https://www.nasjonalmuseet.no/samlingen/objekt/OK-1980-0045","Erverving":"Ervervet 1980","Produksjonsstad":"Norge","Materialkommentar":"Fernissert laminert bøk, polstret, ulltrekk","Mål":"H 51,5 x B 50,8 x D 71,8 cm Høyde: 51,5 cm Dybde: 71,8 cm Bredde: 50,8 cm","Stilperiode":"Postmodernisme","Hundreår":"1900-talet","Frå år":1979,"Til år":1979,"Høgde (cm)":51.5,"Breidde (cm)":50.8,"Djupn (cm)":71.8,"Setehøgde (cm)":51.5,"Materialar":"[\"Bøk\",\"Ull\",\"Kryssfiner\"]","Teknikk":"[\"Polstring\",\"Skruing\",\"Laminering\",\"Formbøying\"]","Emneord":"[\"Møbel\"]"},"content":"<image source=\"https://ms01.nasjonalmuseet.no/iip/?iiif=/tif/92588.tif/full/full/0/default.jpg\">OK-1980-0045</image>"},{"properties":{"Name":"Stol (OK-11528A)","Objekt-ID":"OK-11528A","Betegnelse":"Stol","Datering":"Ca. 1700","Nasjonalmuseet":"https://www.nasjonalmuseet.no/samlingen/objekt/OK-11528A","Erverving":"Testamentarisk gave, innkommet 1946","Produksjonsstad":"Norge","Materialkommentar":"Bjørk, relieffskåret, dels gjennombrutt dekor, bemalt gyllenlærstrekk (sekundært), metallstifter","Mål":"H 127,5 cm x B 53,5 cm x D 63 cm Høyde: 46,5 cm Dybde: 40,5 cm Bredde: 49 cm","Hundreår":"1700-talet","Frå år":1700,"Til år":1700,"Setehøgde (cm)":46.5,"Materialar":"[\"Bjørk\",\"Lær\",\"Kryssfiner\"]","Teknikk":"[\"Tapping\",\"Plugging\",\"Polstring\"]","Emneord":"[\"Møbel\"]"},"content":"<image source=\"https://ms01.nasjonalmuseet.no/iip/?iiif=/tif/94811.tif/full/full/0/default.jpg\">OK-11528A</image>"},{"properties":{"Name":"Reflex 1 produsents tittel","Objekt-ID":"NMK.2005.0646","Betegnelse":"Stol","Datering":"1999","Nasjonalmuseet":"https://www.nasjonalmuseet.no/samlingen/objekt/NMK.2005.0646","Erverving":"Ervervet 2005","Produksjonsstad":"Norge","Materialkommentar":"Beiset, fargelakkert og fernissert kryssfiner og ask med dreid dekor, nylontau og sveiset stål.","Mål":"H 120 x B 81 x D 80 cm Høyde: 120 cm Dybde: 80 cm Bredde: 81 cm","Stilperiode":"Postmodernisme","Hundreår":"1900-talet","Frå år":1999,"Til år":1999,"Høgde (cm)":120,"Breidde (cm)":81,"Djupn (cm)":80,"Setehøgde (cm)":120,"Materialar":"[\"Kryssfiner\",\"Stål\",\"Polyamid\",\"Ask\"]","Teknikk":"[\"Sveising\"]","Emneord":"[\"Møbel\",\"Design\",\"Prototyp\"]"},"content":"<image source=\"https://ms01.nasjonalmuseet.no/iip/?iiif=/tif/08736.tif/full/full/0/default.jpg\">NMK.2005.0646</image>"},{"properties":{"Name":"Stol (OK-08607B)","Objekt-ID":"OK-08607B","Betegnelse":"Stol","Datering":"Midten av 1700-tallet","Nasjonalmuseet":"https://www.nasjonalmuseet.no/samlingen/objekt/OK-08607B","Erverving":"Gave 1912","Produksjonsstad":"Norge","Materialkommentar":"Beiset bjørk med skåret dekor, stoltrekk av bomullspiqué håndbrodert med ulltråd","Mål":"H 105,5 x B 52 x D 48 cm Dybde: 48 cm Bredde: 52 cm Høyde: 105,5 cm","Stilperiode":"Queen Anne","Hundreår":"1700-talet","Frå år":1700,"Til år":1700,"Høgde (cm)":105.5,"Breidde (cm)":52,"Djupn (cm)":48,"Setehøgde (cm)":105.5,"Materialar":"[\"Bjørk\",\"Furu\",\"Bomull\",\"Ull\"]","Emneord":"[\"Møbel\"]"},"content":"<image source=\"https://ms01.nasjonalmuseet.no/iip/?iiif=/tif/OK-08607B.tif/full/full/0/default.jpg\">OK-08607B</image>"}]